trai_dev/__init__.py
trai_dev/my_maths.py
trai_dev-0.0.1.dist-info/LICENSE
trai_dev-0.0.1.dist-info/METADATA
trai_dev-0.0.1.dist-info/WHEEL
trai_dev-0.0.1.dist-info/RECORD
